LICENSE.APACHE
LICENSE.BSD
MANIFEST.in
README.md
pyproject.toml
setup.cfg
setup.py
/var/folders/kl/dts181116sx5h54wcp5vvtv40000gn/T/tmpes8oves8/tmp/fastpbkdf2/fastpbkdf2-1.0.0/fastpbkdf2.c
/var/folders/kl/dts181116sx5h54wcp5vvtv40000gn/T/tmptgacbimx/tmp/fastpbkdf2/fastpbkdf2-1.0.0/fastpbkdf2.c
src/build_fastpbkdf2.py
src/fastpbkdf2.tar.gz
src/msfastpbkdf2/__init__.py
src/msfastpbkdf2.egg-info/PKG-INFO
src/msfastpbkdf2.egg-info/SOURCES.txt
src/msfastpbkdf2.egg-info/dependency_links.txt
src/msfastpbkdf2.egg-info/not-zip-safe
src/msfastpbkdf2.egg-info/requires.txt
src/msfastpbkdf2.egg-info/top_level.txt